cai/__init__.py
cai/api/__init__.py
cai/api/base.py
cai/api/client.py
cai/api/error.py
cai/api/flow.py
cai/api/friend.py
cai/api/group.py
cai/api/login.py
cai/client/__init__.py
cai/client/command.py
cai/client/config_push/__init__.py
cai/client/config_push/command.py
cai/client/config_push/jce.py
cai/client/events/__init__.py
cai/client/events/base.py
cai/client/events/common.py
cai/client/events/friend.py
cai/client/events/group.py
cai/client/friendlist/__init__.py
cai/client/friendlist/command.py
cai/client/friendlist/jce.py
cai/client/heartbeat/__init__.py
cai/client/highway/__init__.py
cai/client/highway/decoders.py
cai/client/highway/encoders.py
cai/client/highway/frame.py
cai/client/highway/highway.py
cai/client/highway/models.py
cai/client/highway/utils.py
cai/client/message_service/__init__.py
cai/client/message_service/command.py
cai/client/message_service/decoders.py
cai/client/message_service/encoders.py
cai/client/message_service/jce.py
cai/client/message_service/models.py
cai/client/models.py
cai/client/multi_msg/__init__.py
cai/client/multi_msg/command.py
cai/client/multi_msg/decoders.py
cai/client/multi_msg/forward.py
cai/client/multi_msg/long_msg.py
cai/client/online_push/__init__.py
cai/client/online_push/command.py
cai/client/online_push/decoders.py
cai/client/online_push/jce.py
cai/client/packet.py
cai/client/pkg_builder/__init__.py
cai/client/pkg_builder/oidb.py
cai/client/pkg_builder/svc_msg.py
cai/client/qq_service/__init__.py
cai/client/qq_service/jce.py
cai/client/session.py
cai/client/sso_server/__init__.py
cai/client/sso_server/jce.py
cai/client/status_service/__init__.py
cai/client/status_service/command.py
cai/client/status_service/jce.py
cai/client/wtlogin/__init__.py
cai/client/wtlogin/oicq.py
cai/client/wtlogin/tlv.py
cai/connection/__init__.py
cai/connection/utils.py
cai/contrib/__init__.py
cai/contrib/login_resolver.py
cai/exceptions.py
cai/log.py
cai/pb/__init__.py
cai/pb/highway/__init__.py
cai/pb/highway/long_msg/__init__.py
cai_bot-0.1.2.dist-info/METADATA
cai_bot-0.1.2.dist-info/WHEEL
cai_bot-0.1.2.dist-info/licenses/LICENSE
cai_bot-0.1.2.dist-info/RECORD
