Metadata-Version: 2.1
Name: cai-bot
Version: 0.1.2
Summary: A QQ protocol framework
Author-Email: yanyongyu <yanyongyu_1@126.com>, wyapx <a1025952421@outlook.com>
License: AGPL-3.0
Requires-Python: >=3.7
Requires-Dist: rtea>=0.3.4
Requires-Dist: jcestruct>=0.1.5
Requires-Dist: protobuf>=4.22.1
Requires-Dist: cachetools>=5.3.0
Requires-Dist: cryptography>=39.0.2
Requires-Dist: typing-extensions>=4.5.0
